MANIFEST.in
README.rst
pyproject.toml
requirements.core.txt
requirements.txt
setup.py
core_module_auto_key_app/__init__.py
core_module_auto_key_app.egg-info/PKG-INFO
core_module_auto_key_app.egg-info/SOURCES.txt
core_module_auto_key_app.egg-info/dependency_links.txt
core_module_auto_key_app.egg-info/requires.txt
core_module_auto_key_app.egg-info/top_level.txt
core_module_auto_key_app/components/__init__.py
core_module_auto_key_app/components/auto_key/__init__.py
core_module_auto_key_app/components/auto_key/api.py
core_module_auto_key_app/components/auto_key/models.py
core_module_auto_key_app/views/__init__.py
core_module_auto_key_app/views/views.py
tests/__init__.py
tests/test_settings.py