Metadata-Version: 1.0
Name: core-module-auto-key-app
Version: 1.20.0
Summary: Auto key module for the parser core project
Home-page: https://github.com/usnistgov/core_module_auto_key_app
Author: NIST IT Lab
Author-email: itl_inquiries@nist.gov
License: UNKNOWN
Platform: UNKNOWN
